wsgicli.py
wsgicli-0.4.0.dist-info/DESCRIPTION.rst
wsgicli-0.4.0.dist-info/METADATA
wsgicli-0.4.0.dist-info/RECORD
wsgicli-0.4.0.dist-info/WHEEL
wsgicli-0.4.0.dist-info/entry_points.txt
wsgicli-0.4.0.dist-info/metadata.json
wsgicli-0.4.0.dist-info/top_level.txt
