Metadata-Version: 2.0
Name: wsgicli
Version: 0.4.0
Summary: Command Line Interface for developing WSGI application.
Home-page: https://github.com/kobinpy/wsgicli
Author: Masashi Shibata <contact@c-bata.link>
Author-email: contact@c-bata.link
License: MIT License
Keywords: web framework wsgi
Platform: UNKNOWN
Classifier: Development Status :: 2 - Pre-Alpha
Classifier: Intended Audience :: Developers
Classifier: License :: OSI Approved :: MIT License
Classifier: Topic :: Internet :: WWW/HTTP :: WSGI
Classifier: Environment :: Web Environment
Classifier: Programming Language :: Python
Classifier: Programming Language :: Python :: 3
Classifier: Programming Language :: Python :: 3 :: Only
Classifier: Programming Language :: Python :: 3.3
Classifier: Programming Language :: Python :: 3.4
Classifier: Programming Language :: Python :: 3.5
Classifier: Programming Language :: Python :: 3.6
Requires-Dist: click
Requires-Dist: wsgi-lineprof
Requires-Dist: wsgi-static-middleware
